ZetcodeKotlinJiaochengChuyiFix1/README.md
ZetcodeKotlinJiaochengChuyiFix1/__init__.py
ZetcodeKotlinJiaochengChuyiFix1/__main__.py
ZetcodeKotlinJiaochengChuyiFix1/file.epub
ZetcodeKotlinJiaochengChuyiFix1/index.html
ZetcodeKotlinJiaochengChuyiFix1/css/__init__.py
ZetcodeKotlinJiaochengChuyiFix1/css/annotations.css
ZetcodeKotlinJiaochengChuyiFix1/css/main.css
ZetcodeKotlinJiaochengChuyiFix1/css/normalize.css
ZetcodeKotlinJiaochengChuyiFix1/css/popup.css
ZetcodeKotlinJiaochengChuyiFix1/font/__init__.py
ZetcodeKotlinJiaochengChuyiFix1/font/fontello.eot
ZetcodeKotlinJiaochengChuyiFix1/font/fontello.svg
ZetcodeKotlinJiaochengChuyiFix1/font/fontello.ttf
ZetcodeKotlinJiaochengChuyiFix1/font/fontello.woff
ZetcodeKotlinJiaochengChuyiFix1/img/__init__.py
ZetcodeKotlinJiaochengChuyiFix1/img/annotator-glyph-sprite.png
ZetcodeKotlinJiaochengChuyiFix1/img/annotator-icon-sprite.png
ZetcodeKotlinJiaochengChuyiFix1/img/apple-touch-icon.png
ZetcodeKotlinJiaochengChuyiFix1/img/cancelfullscreen.png
ZetcodeKotlinJiaochengChuyiFix1/img/close.png
ZetcodeKotlinJiaochengChuyiFix1/img/fullscreen.png
ZetcodeKotlinJiaochengChuyiFix1/img/loader.gif
ZetcodeKotlinJiaochengChuyiFix1/img/menu-icon.png
ZetcodeKotlinJiaochengChuyiFix1/img/save.png
ZetcodeKotlinJiaochengChuyiFix1/img/saved.png
ZetcodeKotlinJiaochengChuyiFix1/img/settings-s.png
ZetcodeKotlinJiaochengChuyiFix1/img/settings.png
ZetcodeKotlinJiaochengChuyiFix1/img/star.png
ZetcodeKotlinJiaochengChuyiFix1/js/__init__.py
ZetcodeKotlinJiaochengChuyiFix1/js/epub.js
ZetcodeKotlinJiaochengChuyiFix1/js/epub.min.js
ZetcodeKotlinJiaochengChuyiFix1/js/epub.min.map
ZetcodeKotlinJiaochengChuyiFix1/js/hooks.min.js
ZetcodeKotlinJiaochengChuyiFix1/js/hooks.min.map
ZetcodeKotlinJiaochengChuyiFix1/js/reader.js
ZetcodeKotlinJiaochengChuyiFix1/js/reader.js.map
ZetcodeKotlinJiaochengChuyiFix1/js/reader.min.js
ZetcodeKotlinJiaochengChuyiFix1/js/reader.min.map
ZetcodeKotlinJiaochengChuyiFix1/js/hooks/__init__.py
zetcode_kotlin_jiaocheng_chuyi_fix1-2025.3.24.0.dist-info/METADATA
zetcode_kotlin_jiaocheng_chuyi_fix1-2025.3.24.0.dist-info/WHEEL
zetcode_kotlin_jiaocheng_chuyi_fix1-2025.3.24.0.dist-info/entry_points.txt
zetcode_kotlin_jiaocheng_chuyi_fix1-2025.3.24.0.dist-info/top_level.txt
zetcode_kotlin_jiaocheng_chuyi_fix1-2025.3.24.0.dist-info/RECORD
